grepxl.py
grepxl-0.1.10.dist-info/METADATA
grepxl-0.1.10.dist-info/WHEEL
grepxl-0.1.10.dist-info/entry_points.txt
grepxl-0.1.10.dist-info/top_level.txt
grepxl-0.1.10.dist-info/RECORD
