Metadata-Version: 2.4
Name: grepxl
Version: 0.1.10
Summary: Add your description here
Requires-Python: >=3.12
Requires-Dist: pandas>=2.2.3
Requires-Dist: python-calamine>=0.5.3
Requires-Dist: rich-tools>=0.5.1
